cowdict/__init__.py
cowdict/cowdict.py
cowdict-0.2.dist-info/DESCRIPTION.rst
cowdict-0.2.dist-info/METADATA
cowdict-0.2.dist-info/RECORD
cowdict-0.2.dist-info/WHEEL
cowdict-0.2.dist-info/metadata.json
cowdict-0.2.dist-info/top_level.txt
